confactory/__init__.py
confactory/argparse.py
confactory/catalog.py
confactory/common.py
confactory/config.py
confactory/converters.py
confactory/jsonnet.py
confactory/plugins.py
confactory/py.typed
confactory/validators.py
confactory-0.1.dist-info/METADATA
confactory-0.1.dist-info/WHEEL
confactory-0.1.dist-info/licenses/LICENSE
confactory-0.1.dist-info/RECORD
