Metadata-Version: 2.1
Name: confactory
Version: 0.1
Summary: Construct Python objects directly from configuration files
Project-URL: Source, https://git.sr.ht/~dojoteef/confactory
Project-URL: Mailing List, https://lists.sr.ht/~dojoteef/confactory
Author-email: Nader Akoury <~dojoteef/confactory-devel@lists.sr.ht>
License-Expression: MIT
License-File: LICENSE
Classifier: Development Status :: 3 - Alpha
Classifier: Intended Audience :: Developers
Classifier: License :: OSI Approved :: MIT License
Classifier: Operating System :: OS Independent
Classifier: Programming Language :: Python :: 3
Classifier: Programming Language :: Python :: 3 :: Only
Classifier: Programming Language :: Python :: 3.6
Classifier: Programming Language :: Python :: 3.7
Classifier: Programming Language :: Python :: 3.8
Classifier: Programming Language :: Python :: 3.9
Classifier: Programming Language :: Python :: 3.10
Classifier: Programming Language :: Python :: 3.11
Classifier: Programming Language :: Python :: 3.12
Classifier: Typing :: Typed
Requires-Python: >=3.6
Requires-Dist: attrs>=20.3.0
Requires-Dist: jsonnet<1.0,>=0.12.1
Requires-Dist: typing-extensions; python_version < '3.8'
Provides-Extra: codeqa
Requires-Dist: ruff; extra == 'codeqa'
Provides-Extra: dev
Requires-Dist: confactory[codeqa]; extra == 'dev'
Requires-Dist: confactory[formatters]; extra == 'dev'
Requires-Dist: confactory[typing]; extra == 'dev'
Provides-Extra: formatters
Requires-Dist: black; extra == 'formatters'
Requires-Dist: isort; extra == 'formatters'
Provides-Extra: typing
Requires-Dist: mypy; extra == 'typing'
